devgen/__init__.py
devgen/ai.py
devgen/utils.py
devgen/cli/__init__.py
devgen/cli/changelog.py
devgen/cli/commit.py
devgen/cli/config.py
devgen/cli/gitignore.py
devgen/cli/license.py
devgen/cli/main.py
devgen/cli/release.py
devgen/cli/setup.py
devgen/modules/__init__.py
devgen/modules/changelog_generator.py
devgen/modules/commit_generator.py
devgen/modules/gitignore_generator.py
devgen/modules/license_generator.py
devgen/modules/release_note_generator.py
devgen/providers/__init__.py
devgen/providers/anthropic.py
devgen/providers/gemini.py
devgen/providers/huggingface.py
devgen/providers/openai.py
devgen/providers/openrouter.py
devgen/templates/commit/commit_message.j2
devgen/templates/licenses/agpl-3.0.json
devgen/templates/licenses/apache-2.0.json
devgen/templates/licenses/bsd-2-clause.json
devgen/templates/licenses/bsd-3-clause.json
devgen/templates/licenses/bsl-1.0.json
devgen/templates/licenses/cc0-1.0.json
devgen/templates/licenses/epl-2.0.json
devgen/templates/licenses/gpl-2.0.json
devgen/templates/licenses/gpl-3.0.json
devgen/templates/licenses/lgpl-2.1.json
devgen/templates/licenses/mit.json
devgen/templates/licenses/mpl-2.0.json
devgen/templates/licenses/unlicense.json
devgen_cli-0.2.4.dist-info/licenses/LICENSE
devgen_cli-0.2.4.dist-info/METADATA
devgen_cli-0.2.4.dist-info/WHEEL
devgen_cli-0.2.4.dist-info/entry_points.txt
devgen_cli-0.2.4.dist-info/top_level.txt
devgen_cli-0.2.4.dist-info/RECORD
