Metadata-Version: 2.4
Name: devgen-cli
Version: 0.2.4
Summary: A collection of developer tools
Home-page: https://github.com/S4NKALP/devgen
Author: Sankalp Tharu
Author-email: Sankalp Tharu <sankalptharu50028@gmail.com>
License: GPL-3.0-or-later
Project-URL: Homepage, https://github.com/S4NKALP/devgen
Keywords: devgen,cli,git,changelog,gitignore,license,commit-generator,commit
Classifier: Development Status :: 3 - Alpha
Classifier: Intended Audience :: Developers
Classifier: License :: OSI Approved :: GNU General Public License v3 or later (GPLv3+)
Classifier: Operating System :: OS Independent
Classifier: Programming Language :: Python :: 3
Classifier: Programming Language :: Python :: 3.7
Classifier: Programming Language :: Python :: 3.8
Classifier: Programming Language :: Python :: 3.9
Classifier: Programming Language :: Python :: 3.10
Requires-Python: >=3.10
License-File: LICENSE
Requires-Dist: anthropic>=0.75.0
Requires-Dist: google-generativeai>=0.8.5
Requires-Dist: jinja2>=3.1.6
Requires-Dist: openai>=2.11.0
Requires-Dist: pyyaml>=6.0.3
Requires-Dist: questionary>=2.1.1
Requires-Dist: requests>=2.32.5
Requires-Dist: rich>=14.2.0
Requires-Dist: toml>=0.10.2
Requires-Dist: typer>=0.20.0
Dynamic: author
Dynamic: home-page
Dynamic: license-file
Dynamic: requires-python
